hexarch_cli/__init__.py
hexarch_cli/__main__.py
hexarch_cli/cli.py
hexarch_cli/context.py
hexarch_cli/db.py
hexarch_cli/rules_engine.py
hexarch_cli/api/__init__.py
hexarch_cli/api/auth.py
hexarch_cli/api/client.py
hexarch_cli/commands/__init__.py
hexarch_cli/commands/config.py
hexarch_cli/commands/db.py
hexarch_cli/commands/decision.py
hexarch_cli/commands/entitlement.py
hexarch_cli/commands/metrics.py
hexarch_cli/commands/policy.py
hexarch_cli/commands/rule.py
hexarch_cli/config/__init__.py
hexarch_cli/config/config.py
hexarch_cli/config/schemas.py
hexarch_cli/logging/__init__.py
hexarch_cli/logging/audit.py
hexarch_cli/output/__init__.py
hexarch_cli/output/colors.py
hexarch_cli/output/formatter.py
hexarch_guardrails/__init__.py
hexarch_guardrails/exceptions.py
hexarch_guardrails/guardian.py
hexarch_guardrails/opa_client.py
hexarch_guardrails/policy_loader.py
hexarch_guardrails/templates.py
hexarch_guardrails-0.4.0.dist-info/licenses/LICENSE
hexarch_guardrails-0.4.0.dist-info/METADATA
hexarch_guardrails-0.4.0.dist-info/WHEEL
hexarch_guardrails-0.4.0.dist-info/entry_points.txt
hexarch_guardrails-0.4.0.dist-info/top_level.txt
hexarch_guardrails-0.4.0.dist-info/RECORD
