Metadata-Version: 2.4
Name: hexarch-guardrails
Version: 0.4.0
Summary: Lightweight policy-driven API protection and guardrails library
Home-page: https://www.noirstack.com/
Author: Noir Stack
Author-email: Noir Stack <hira@noirstack.com>
Maintainer: Hira
Maintainer-email: Hira <hira@noirstack.com>
License: MIT License
Project-URL: Homepage, https://www.noirstack.com/
Project-URL: Repository, https://github.com/no1rstack/hexarch-guardrails
Project-URL: Documentation, https://github.com/no1rstack/hexarch-guardrails#readme
Project-URL: Issues, https://github.com/no1rstack/hexarch-guardrails/issues
Keywords: policy,guardrails,api,protection,opa
Classifier: Development Status :: 4 - Beta
Classifier: Intended Audience :: Developers
Classifier: License :: OSI Approved :: MIT License
Classifier: Programming Language :: Python :: 3.8
Classifier: Programming Language :: Python :: 3.9
Classifier: Programming Language :: Python :: 3.10
Classifier: Programming Language :: Python :: 3.11
Classifier: Programming Language :: Python :: 3.12
Requires-Python: >=3.8
License-File: LICENSE
Requires-Dist: requests>=2.28.0
Requires-Dist: pyyaml>=6.0
Requires-Dist: python-dotenv>=0.21.0
Requires-Dist: click>=8.1.0
Requires-Dist: pydantic>=2.0
Requires-Dist: tabulate>=0.9.0
Requires-Dist: colorama>=0.4.6
Provides-Extra: cli
Requires-Dist: click>=8.1.0; extra == "cli"
Requires-Dist: pydantic>=2.0; extra == "cli"
Requires-Dist: tabulate>=0.9.0; extra == "cli"
Requires-Dist: colorama>=0.4.6; extra == "cli"
Provides-Extra: dev
Requires-Dist: pytest>=7.0; extra == "dev"
Requires-Dist: pytest-cov>=4.0; extra == "dev"
Requires-Dist: black>=23.0; extra == "dev"
Requires-Dist: flake8>=5.0; extra == "dev"
Dynamic: author
Dynamic: home-page
Dynamic: license-file
Dynamic: maintainer
Dynamic: requires-python
